LICENSE.pdf
MANIFEST.in
README.md
requirements.txt
setup.py
OASYS1_WONDER.egg-info/PKG-INFO
OASYS1_WONDER.egg-info/SOURCES.txt
OASYS1_WONDER.egg-info/dependency_links.txt
OASYS1_WONDER.egg-info/entry_points.txt
OASYS1_WONDER.egg-info/namespace_packages.txt
OASYS1_WONDER.egg-info/requires.txt
OASYS1_WONDER.egg-info/top_level.txt
orangecontrib/__init__.py
orangecontrib/wonder/__init__.py
orangecontrib/wonder/fit/__init__.py
orangecontrib/wonder/fit/__test/__init__.py
orangecontrib/wonder/fit/__test/test.py
orangecontrib/wonder/fit/__test/wppm_functions_multipool.py
orangecontrib/wonder/fit/fitters/__init__.py
orangecontrib/wonder/fit/fitters/fitter.py
orangecontrib/wonder/fit/fitters/fitter_factory.py
orangecontrib/wonder/fit/fitters/fitter_minpack.py
orangecontrib/wonder/fit/functions/__init__.py
orangecontrib/wonder/fit/functions/chemical_formula_parser.py
orangecontrib/wonder/fit/functions/gsasii_functions.py
orangecontrib/wonder/fit/functions/wppm_functions.py
orangecontrib/wonder/fit/functions/data/__init__.py
orangecontrib/wonder/fit/functions/data/atomic_scattering_factor_coefficients.dat
orangecontrib/wonder/fit/functions/data/delta_l_files/100.FTinfo
orangecontrib/wonder/fit/functions/data/delta_l_files/110.FTinfo
orangecontrib/wonder/fit/functions/data/delta_l_files/111.FTinfo
orangecontrib/wonder/fit/functions/data/delta_l_files/200.FTinfo
orangecontrib/wonder/fit/functions/data/delta_l_files/220.FTinfo
orangecontrib/wonder/fit/functions/data/delta_l_files/222.FTinfo
orangecontrib/wonder/fit/functions/data/delta_l_files/311.FTinfo
orangecontrib/wonder/fit/functions/data/delta_l_files/331.FTinfo
orangecontrib/wonder/fit/functions/data/delta_l_files/333.FTinfo
orangecontrib/wonder/fit/functions/data/delta_l_files/400.FTinfo
orangecontrib/wonder/fit/functions/data/delta_l_files/420.FTinfo
orangecontrib/wonder/fit/functions/data/delta_l_files/422.FTinfo
orangecontrib/wonder/fit/functions/data/delta_l_files/440.FTinfo
orangecontrib/wonder/fit/functions/data/delta_l_files/442.FTinfo
orangecontrib/wonder/fit/functions/data/delta_l_files/444.FTinfo
orangecontrib/wonder/fit/functions/data/delta_l_files/511.FTinfo
orangecontrib/wonder/fit/functions/data/delta_l_files/531.FTinfo
