Metadata-Version: 1.1
Name: OASYS1-WONDER
Version: 1.0.45
Summary: Whole POwder PatterN MoDEl in OASYS.
Home-page: https://github.com/WONDER-project/OASYS1-WONDER
Author: Luca Rebuffi, Paolo Scardi
Author-email: lrebuffi@anl.gov, paolo.scardi@unitn.it
License: GPL3+
Keywords: oasys1
Platform: UNKNOWN
Classifier: Development Status :: 1 - Planning
Classifier: Intended Audience :: Education
Classifier: Intended Audience :: Science/Research
Classifier: License :: OSI Approved :: GNU General Public License v3 or later (GPLv3+)
Classifier: Programming Language :: Python :: 3 :: Only
